rov_sent_api/__init__.py
rov_sent_api/exceptions.py
rov_sent_api/sentinel_api.py
rov_sent_api-0.1.24.dist-info/METADATA
rov_sent_api-0.1.24.dist-info/WHEEL
rov_sent_api-0.1.24.dist-info/RECORD
